<annotation>
	<folder>U</folder>
	<filename>Image_1725971071.876472_9.jpg</filename>
	<path>C:\Users\HP\Desktop\SIH\Data\U\Image_1725971071.876472_9.jpg</path>
	<source>
		<database>Unknown</database>
	</source>
	<size>
		<width>640</width>
		<height>480</height>
		<depth>3</depth>
	</size>
	<segmented>0</segmented>
	<object>
		<name>U</name>
		<pose>Unspecified</pose>
		<truncated>0</truncated>
		<difficult>0</difficult>
		<bndbox>
			<xmin>265</xmin>
			<ymin>298</ymin>
			<xmax>386</xmax>
			<ymax>444</ymax>
		</bndbox>
	</object>
</annotation>
